pyvidplayer2/__init__.py
pyvidplayer2/_version.py
pyvidplayer2/cv_reader.py
pyvidplayer2/decord_reader.py
pyvidplayer2/error.py
pyvidplayer2/ffmpeg_reader.py
pyvidplayer2/imageio_reader.py
pyvidplayer2/mixer_handler.py
pyvidplayer2/post_processing.py
pyvidplayer2/pyaudio_handler.py
pyvidplayer2/subtitles.py
pyvidplayer2/video.py
pyvidplayer2/video_player.py
pyvidplayer2/video_pygame.py
pyvidplayer2/video_pyglet.py
pyvidplayer2/video_pyqt.py
pyvidplayer2/video_pyside.py
pyvidplayer2/video_raylib.py
pyvidplayer2/video_reader.py
pyvidplayer2/video_tkinter.py
pyvidplayer2/video_wx.py
pyvidplayer2/webcam.py
pyvidplayer2-0.9.29.dist-info/licenses/LICENSE
pyvidplayer2-0.9.29.dist-info/METADATA
pyvidplayer2-0.9.29.dist-info/WHEEL
pyvidplayer2-0.9.29.dist-info/top_level.txt
pyvidplayer2-0.9.29.dist-info/RECORD
