Metadata-Version: 2.4
Name: pyvidplayer2
Version: 0.9.29
Summary: Reliable, easy, and fast video playback in Python
Author-email: Anray Liu <anrayliu@gmail.com>
License-Expression: MIT
Project-URL: Homepage, https://github.com/anrayliu/pyvidplayer2
Project-URL: Documentation, https://github.com/anrayliu/pyvidplayer2/blob/main/documentation.md
Project-URL: Repository, https://github.com/anrayliu/pyvidplayer2.git
Project-URL: Issues, https://github.com/anrayliu/pyvidplayer2/issues
Keywords: pygame,video,playback,tkinter,pyqt,pyside,pyglet,wxpython
Classifier: Development Status :: 4 - Beta
Classifier: Intended Audience :: Developers
Classifier: Topic :: Multimedia :: Video
Classifier: Topic :: Multimedia :: Video :: Display
Classifier: Topic :: Software Development :: Libraries :: pygame
Classifier: Programming Language :: Python :: 3.8
Classifier: Programming Language :: Python :: 3.9
Classifier: Programming Language :: Python :: 3.10
Classifier: Programming Language :: Python :: 3.11
Classifier: Programming Language :: Python :: 3.12
Classifier: Programming Language :: Python :: 3.13
Classifier: Programming Language :: Python :: 3.14
Requires-Python: >=3.8
License-File: LICENSE
Requires-Dist: numpy
Requires-Dist: opencv-python
Requires-Dist: pygame-ce
Requires-Dist: pysubs2
Requires-Dist: PyAudio
Provides-Extra: all
Requires-Dist: numpy; extra == "all"
Requires-Dist: opencv-python; extra == "all"
Requires-Dist: pygame-ce; extra == "all"
Requires-Dist: PyAudio; extra == "all"
Requires-Dist: pysubs2; extra == "all"
Requires-Dist: yt-dlp; extra == "all"
Requires-Dist: decord; extra == "all"
Requires-Dist: imageio; extra == "all"
Requires-Dist: av; extra == "all"
Requires-Dist: pyglet; extra == "all"
Requires-Dist: PySide6; extra == "all"
Requires-Dist: PyQt6; extra == "all"
Requires-Dist: raylib; extra == "all"
Requires-Dist: wxPython; extra == "all"
Dynamic: license-file
